pursuitlib_qrcode/__init__.py
pursuitlib_qrcode/pdfhelper.py
pursuitlib_qrcode/qrhelper.py
pursuitlib_qrcode-0.2.2.dist-info/METADATA
pursuitlib_qrcode-0.2.2.dist-info/WHEEL
pursuitlib_qrcode-0.2.2.dist-info/top_level.txt
pursuitlib_qrcode-0.2.2.dist-info/RECORD
